{"ast":null,"code":"function post() {\n  var submit = document.getElementById(\"submit_btn\");\n  submit.addEventListener(\"click\", function (e) {\n    console.log(document.getElementById(\"new_article\"));\n    e.preventDefault();\n  });\n}\n;\nwindow.addEventListener('load', post);","map":{"version":3,"names":["post","submit","document","getElementById","addEventListener","e","console","log","preventDefault","window"],"sources":["/Users/admin/projects/ajax_app/app/javascript/post.js"],"sourcesContent":["function post (){\n  const submit = document.getElementById(\"submit_btn\");\n  submit.addEventListener(\"click\", (e) => {\n    console.log(document.getElementById(\"new_article\"));\n    e.preventDefault();\n  });\n};\n\nwindow.addEventListener('load', post);\n"],"mappings":"AAAA,SAASA,IAAI,GAAG;EACd,IAAMC,MAAM,GAAGC,QAAQ,CAACC,cAAc,CAAC,YAAY,CAAC;EACpDF,MAAM,CAACG,gBAAgB,CAAC,OAAO,EAAE,UAACC,CAAC,EAAK;IACtCC,OAAO,CAACC,GAAG,CAACL,QAAQ,CAACC,cAAc,CAAC,aAAa,CAAC,CAAC;IACnDE,CAAC,CAACG,cAAc,EAAE;EACpB,CAAC,CAAC;AACJ;AAAC;AAEDC,MAAM,CAACL,gBAAgB,CAAC,MAAM,EAAEJ,IAAI,CAAC"},"metadata":{},"sourceType":"module","externalDependencies":[]}